README.md
setup.py
cryptonotifier/__init__.py
cryptonotifier/config.py
cryptonotifier/emergency.py
cryptonotifier/formatter.py
cryptonotifier/getdata.py
cryptonotifier/main.py
cryptonotifier/notifier.py
cryptoprice_notifier.egg-info/PKG-INFO
cryptoprice_notifier.egg-info/SOURCES.txt
cryptoprice_notifier.egg-info/dependency_links.txt
cryptoprice_notifier.egg-info/entry_points.txt
cryptoprice_notifier.egg-info/requires.txt
cryptoprice_notifier.egg-info/top_level.txt