Metadata-Version: 2.1
Name: cryptoprice-notifier
Version: 2.3.1
Summary: tool to get crypto price notification
Home-page: https://github.com/anurag-gothi-au6/cryptoprice-notifier
Author: Anurag Gothi
Author-email: ianuraggothi@gmail.com
License: MIT
Keywords: crypto-price,crypto-price-notifier,crypto price,crypto,Crypto
Platform: UNKNOWN
Classifier: Programming Language :: Python :: 3
Classifier: License :: OSI Approved :: MIT License
Classifier: Operating System :: OS Independent
